.coveragerc
.travis.yml
AUTHORS
ChangeLog
LICENSE
MANIFEST.in
README.rst
requirements.txt
setup.cfg
setup.py
tox.ini
docs/Makefile
docs/make.bat
docs/source/conf.py
docs/source/index.rst
docs/source/readme.rst
leonardo_epiceditor/__init__.py
leonardo_epiceditor/urls.py
leonardo_epiceditor/utils.py
leonardo_epiceditor/views.py
leonardo_epiceditor.egg-info/PKG-INFO
leonardo_epiceditor.egg-info/SOURCES.txt
leonardo_epiceditor.egg-info/dependency_links.txt
leonardo_epiceditor.egg-info/not-zip-safe
leonardo_epiceditor.egg-info/pbr.json
leonardo_epiceditor.egg-info/top_level.txt
leonardo_epiceditor/static/lib/js/epiceditor.init.js
leonardo_epiceditor/static/lib/js/epiceditor.min.js
leonardo_epiceditor/static/lib/themes/base/epiceditor.css
leonardo_epiceditor/static/lib/themes/editor/epic-dark.css
leonardo_epiceditor/static/lib/themes/editor/epic-light.css
leonardo_epiceditor/static/lib/themes/preview/bartik.css
leonardo_epiceditor/static/lib/themes/preview/github.css
leonardo_epiceditor/static/lib/themes/preview/preview-dark.css
requirements/default.txt
requirements/markdown.txt
requirements/rest.txt
requirements/tests.txt
tests/cov.sh
tests/local_settings.py
tests/manage.py
tests/testapp/__init__.py
tests/testapp/models.py
tests/testapp/settings.py
tests/testapp/urls.py
tests/testapp/tests/__init__.py
tests/testapp/tests/test_commands.py